{"WorldPos":{"x":22.4376545,"y":-7.230167,"z":8.724477,"normalized":{"x":0.892634869,"y":-0.287636966,"z":0.347084939,"magnitude":1.0,"sqrMagnitude":1.0},"magnitude":25.13643,"sqrMagnitude":631.840149},"Pos":{"x":22.4376545,"y":-7.230167,"z":8.724477,"normalized":{"x":0.892634869,"y":-0.287636966,"z":0.347084939,"magnitude":1.0,"sqrMagnitude":1.0},"magnitude":25.13643,"sqrMagnitude":631.840149},"Rot":{"x":32.9952774,"y":74.3969,"z":20.1349068,"normalized":{"x":0.3935546,"y":0.8873767,"z":0.2401612,"magnitude":1.0,"sqrMagnitude":1.00000012},"magnitude":83.8391342,"sqrMagnitude":7029.001},"Ship":{"shipID":231111899,"shipName":"Spider","valuesList":[{"name":0,"value":399.976746,"max":400.0},{"name":1,"value":60.0,"max":60.0},{"name":2,"value":100.0,"max":100.0},{"name":3,"value":0.0,"max":100.0}],"slots":[{"uid":0,"slotType":1,"slotLevel":1,"button":1,"itemData":{"idName":"termal_laser_v1","value":1.0}},{"uid":2,"slotType":2,"slotLevel":1,"button":-1,"itemData":{"idName":"shield_generator_v1","value":1.0}},{"uid":3,"slotType":3,"slotLevel":1,"button":-1,"itemData":{"idName":"armor","value":1.0}},{"uid":4,"slotType":4,"slotLevel":1,"button":-1,"itemData":{"idName":"cooler_v1","value":1.0}},{"uid":5,"slotType":5,"slotLevel":1,"button":-1,"itemData":{"idName":"generator_light","value":1.0}}]},"Keys":{"MapActive":3,"system_start_on":"Filling Orbital #0"},"Reputations":{},"IsLanded":{"pos":{"x":22.4045753,"y":-7.21388769,"z":8.70034,"normalized":{"x":0.8928315,"y":-0.287476361,"z":0.3467121,"magnitude":1.0,"sqrMagnitude":1.0},"magnitude":25.0938454,"sqrMagnitude":629.7011},"rot":{"x":0.3153413,"y":0.5349248,"z":-0.0309130847,"w":0.7832368,"eulerAngles":{"x":31.8060837,"y":74.3795,"z":19.8767815,"normalized":{"x":0.38182205,"y":0.892902553,"z":0.238614514,"normalized":{"x":0.381822079,"y":0.8929026,"z":0.238614529,"magnitude":1.0,"sqrMagnitude":1.00000012},"magnitude":0.99999994,"sqrMagnitude":0.99999994},"magnitude":83.3008041,"sqrMagnitude":6939.02344},"normalized":{"x":0.315341264,"y":0.534924746,"z":-0.030913081,"w":0.7832367,"eulerAngles":{"x":31.8060875,"y":74.37951,"z":19.8767853,"normalized":{"x":0.38182205,"y":0.892902553,"z":0.238614544,"magnitude":1.0,"sqrMagnitude":0.99999994},"magnitude":83.30081,"sqrMagnitude":6939.02539},"normalized":{"x":0.3153413,"y":0.5349248,"z":-0.0309130829,"w":0.783236742,"eulerAngles":{"x":31.8060875,"y":74.37951,"z":19.8767853,"normalized":{"x":0.38182205,"y":0.892902553,"z":0.238614544,"magnitude":1.0,"sqrMagnitude":0.99999994},"magnitude":83.30081,"sqrMagnitude":6939.02539}}}}},"quests":[],"items":[{"idName":"credit","value":2802.89551}],"shipsInStations":{},"systemsHistory":["Relating 0371692.[35702,24,3837,27,-39345,47]","Permitted 0225748.[31979,82,2395,87,-40102,80]","Knowledge 0458027.[34759,16,799,93,-37756,55]","Shaft 0560465.[35248,96,-262,99,-34870,60]","Filling 0776934.[38322,55,2148,44,-34690,99]"],"playedTime":125.1362620,"startSaveTime":200308}